basalam.backbone_orm-2.2.9-py3.13-nspkg.pth
basalam/backbone_orm/__init__.py
basalam/backbone_orm/api_resource_abstract.py
basalam/backbone_orm/enumerations.py
basalam/backbone_orm/factory_abstract.py
basalam/backbone_orm/migration_abstract.py
basalam/backbone_orm/model_abstract.py
basalam/backbone_orm/model_schema_abstract.py
basalam/backbone_orm/pagination.py
basalam/backbone_orm/parameters.py
basalam/backbone_orm/postgres_connection.py
basalam/backbone_orm/postgres_manager.py
basalam/backbone_orm/postgres_transaction.py
basalam/backbone_orm/query_builder_abstract.py
basalam/backbone_orm/relation.py
basalam/backbone_orm/relation_applier.py
basalam/backbone_orm/repository_abstract.py
basalam/backbone_orm/seeder_abstract.py
basalam_backbone_orm-2.2.9.dist-info/licenses/LICENSE
basalam_backbone_orm-2.2.9.dist-info/METADATA
basalam_backbone_orm-2.2.9.dist-info/WHEEL
basalam_backbone_orm-2.2.9.dist-info/namespace_packages.txt
basalam_backbone_orm-2.2.9.dist-info/top_level.txt
basalam_backbone_orm-2.2.9.dist-info/RECORD
